tf_seal-0.1.0.data/purelib/tf_seal/__init__.py
tf_seal-0.1.0.data/purelib/tf_seal/python/__init__.py
tf_seal-0.1.0.data/purelib/tf_seal/python/tensor.py
tf_seal-0.1.0.data/purelib/tf_seal/python/ops/__init__.py
tf_seal-0.1.0.data/purelib/tf_seal/python/ops/_seal_ops.so
tf_seal-0.1.0.data/purelib/tf_seal/python/ops/seal_ops.py
tf_seal-0.1.0.dist-info/METADATA
tf_seal-0.1.0.dist-info/WHEEL
tf_seal-0.1.0.dist-info/top_level.txt
tf_seal-0.1.0.dist-info/RECORD
