Metadata-Version: 2.1
Name: tf-seal
Version: 0.1.0
Summary: Bridge between TensorFlow and the Microsoft SEAL homomorphic encryption library.
Home-page: https://github.com/tf-encrypted/tf-seal
Author: The TF Encrypted Authors
Author-email: contact@tf-encrypted.io
License: Apache License 2.0
Platform: UNKNOWN
Classifier: Programming Language :: Python :: 3
Classifier: License :: OSI Approved :: Apache Software License
Classifier: Development Status :: 2 - Pre-Alpha
Classifier: Operating System :: OS Independent
Classifier: Topic :: Scientific/Engineering :: Artificial Intelligence
Classifier: Topic :: Security :: Cryptography
Requires-Python: ==3.7.*
Requires-Dist: numpy (>=1.14)
Requires-Dist: tf-nightly (<2,>=1.14.0)
Provides-Extra: tf
Requires-Dist: tf-nightly (<2,>=1.14.0) ; extra == 'tf'
